CHANGES.md
LICENSE.md
MANIFEST.in
README.md
requirements.txt
requirements_dev.txt
setup.cfg
setup.py
summarizer/__init__.py
summarizer/parser.py
summarizer/sanitizer.py
summarizer/summarizer.py
summarizer.egg-info/PKG-INFO
summarizer.egg-info/SOURCES.txt
summarizer.egg-info/dependency_links.txt
summarizer.egg-info/requires.txt
summarizer.egg-info/top_level.txt
summarizer/trainer/__init__.py
summarizer/trainer/english.json
summarizer/trainer/english.pickle
summarizer/trainer/stop_words.txt