Metadata-Version: 1.1
Name: summarizer
Version: 0.0.5
Summary: A text summarizer
Home-page: https://github.com/michigan-com/summarizer
Author: Eric Bower
Author-email: neurosnap@gmail.com
License: The MIT License (MIT)
